{
    "schemaVer":  1,
    "channel":  "stable",
    "app":  {
                "latestVersion":  "1.0.1",
                "minSupportedVersion":  "0.1.0",
                "installer":  {
                                  "url":  "https://github.com/nari-git/MoriageLog/releases/download/v1.0.1/MoriageLog-Setup-1.0.1.exe",
                                  "sha256":  "93D43F01E66895EB70C7731CDF269DE30DA0A1C3A6126F9A8122C7D9B051EED0",
                                  "sizeBytes":  180729309,
                                  "releaseNotes":  "v1.0.0 で見つかった不具合の修正と、演出まわりの機能追加です。\n設定の作り直しは必要ありません。そのまま更新してお使いいただけます。\n\n## 重要な修正\n\n###更新ボタン内の処理変更\n更新処理の仕様を変更したため、公式サイトより再ダウンロードを行い、再度上書きインストールを行ってください。\n\n### TikTokのコメントが取得できなくなっていた問題\n\nTikTok側の作りが変わり、コメント本文の目印が無くなったため、コメントを拾えなくなっていました。新しい作りに合わせて修正しています。**設定は更新時に自動で書き換わる**ので、操作は必要ありません。\n\nあわせて、今後サイト側の作りが変わっても気づけるように、うまく取得できないときは設定画面の状態欄に理由を表示するようにしました（「ログインが必要そう」「コメント欄が見つからない」など）。\n\n### 接続すると配信の音がもりあげログから出る問題\n\nブラウザ方式のサイト（TikTok・ニコ生・ツイキャス・ふわっち・KICK・SHOWROOM・ミクチャ・ミラティブ・bilibili）に接続すると、コメント取得のために裏で開いている配信ページの音が鳴ってしまっていました。音が出ないようにしました。ログイン画面も同様です。\n\n### 演出の設定が保存されない問題\n\n演出（初コメント・MVP・フォローなど）の位置・色・文字の大きさを変えても、保存されないことがありました。修正しています。\n\n### プレビューが真っ白になる問題\n\n設定画面のプレビューが白いまま表示され、背景（市松・黒・グリーン）を切り替えても変わらないことがありました。ステッカー、コメント表示のデザイン編集、演出、ランキングなど、プレビューのある画面をまとめて修正しています。\n\n## 新しくできること\n\n### 演出ごとに「見せ方」と「動き」を選べるようになりました\n\nこれまで、演出はどれも同じ形の箱で出ていました。演出の種類ごとに、5つの見せ方から選べます。\n\n- 箱で出す（これまでどおり）\n- 画面中央に大きく\n- 帯が横から滑り込む\n- 横に流れるテロップ\n- スタッフロール風に流す\n\n出るときの動き（ポップ／弾む／下から／めくる／ズーム）も、演出ごとに変えられます。**今までの設定はそのまま**なので、見た目が勝手に変わることはありません。\n\n### お礼ロールをスタッフロール風に流せるようになりました\n\n配信の締めに、その日コメントをくれた方のお名前を、映画のエンドロールのように下から上へ流せます。人数に合わせて流れる速さが変わります。これまでの「1人ずつ表示」も残してあるので、設定で選べます。\n\n### ルーレットで、人以外も抽選できるようになりました\n\nこれまでは参加した人からの抽選だけでしたが、「抽選のもと」を選べるようになりました。\n\n- **参加した人**（これまでどおり）\n- **用意したリスト** … ごはん決め、お題出し、罰ゲームなどに\n- **視聴者が出した案** … 「抽選 ラーメン」のようにコメントしてもらった案から選ぶ\n\n項目ごとに「出やすさ」と色を決められます。当選したときの文言も変えられます。\n\n### ミニゲームの内容を、その場で変えられるようになりました\n\nルーレットの項目とおみくじの結果を、ミニゲームの画面から直接編集できるようになりました。**OBSに貼ったURLはそのままで内容が切り替わる**ので、配信中でも貼り替えの手間がありません。\n\n## 改善\n\n- ステッカーの登録欄を読みやすくしました（「有効」が2行に折り返したり、ファイル名が見えなくなっていたのを整理）\n- 設定画面から、触る必要のない項目を隠しました（YouTube・ミラティブの内部設定など）\n- 使わなくなっていた入力欄を取り除きました\n- ルーレットとおみくじの「ベータ」表記を外しました\n"
                              }
            }
}